{
  "id": "aws_rds_dynamodb",
  "topic": "aws_data_platform",
  "track": "aws_enterprise",
  "module": "data_ai",
  "order": 1,
  "title": {"en": "RDS vs DynamoDB: Relational & NoSQL at Scale"},
  "description": {"en": "Choose between RDS/Aurora and DynamoDB with an engineer's honesty — consistency models, scaling behavior, and the RCU/WCU capacity math that prices every DynamoDB table."},
  "xp_reward": 105,
  "next_unlock": "aws_redshift_glue_athena",
  "story_variants": {"en": "## The Most Expensive Decision After the VPC\n\nDatabase choice is sticky. Applications adapt to their database's shape — query patterns, transactions, consistency expectations — and migrating later means rewriting the assumptions baked into ten thousand lines of code. The RDS-versus-DynamoDB question is really a question about your access patterns, your scaling curve, and how much operational database expertise you intend to employ.\n\n## RDS and Aurora: Relational, Managed, Familiar\n\n**RDS** runs managed instances of PostgreSQL, MySQL, MariaDB, SQL Server, Oracle, and Db2 — AWS handles patching, automated backups (point-in-time recovery from continuous backups plus snapshots), and **Multi-AZ** failover (synchronous replication to a standby; failover typically completes in tens of seconds, or faster with Multi-AZ DB clusters that add readable standbys). **Read replicas** (asynchronous) scale reads and feed cross-region DR.\n\n**Aurora** is AWS's cloud-native re-architecture of MySQL/PostgreSQL: the storage layer is a distributed, self-healing volume replicating **six copies across three AZs**, decoupled from compute. Consequences enterprises care about:\n\n- Failover promotes a replica against shared storage — typically ~30 seconds, no data rebuild.\n- Up to 15 low-lag read replicas on the same storage volume.\n- **Aurora Serverless v2** scales compute in fine-grained ACU increments — genuinely useful for spiky or multi-tenant workloads; the pricing model is per-ACU-hour instead of per-instance.\n- **Global Database** replicates storage cross-region with ~1s typical lag for regional DR and read locality.\n\nRDS's limits are the relational model's limits: vertical scaling has a ceiling (a very high one — but a single writer is still a single writer), schema changes on huge tables demand care, and connection storms from serverless callers require **RDS Proxy**.\n\n## DynamoDB: The Database That Refuses to Fall Over\n\nDynamoDB is a fully managed key-value/document store with a different contract: **single-digit-millisecond latency at any scale**, no instances, no patching, no connection pools. Data is partitioned by **partition key** (hashed for distribution); an optional **sort key** enables range queries within a partition. You get exactly the queries your keys support — plus **Global Secondary Indexes** (different key shape, eventually consistent, own capacity) — and nothing else. No joins. No ad-hoc queries. That constraint is the price of the scaling guarantee.\n\nThe capacity model is where engineering meets billing:\n\n| Unit | Buys you |\n|---|---|\n| 1 RCU | One **strongly consistent** read/sec up to 4 KB, or TWO **eventually consistent** reads/sec |\n| 1 WCU | One write/sec up to 1 KB |\n| Transactional ops | 2x the RCU/WCU cost |\n\nItem sizes round UP: a 7 KB strongly consistent read costs ceil(7/4) = 2 RCU; the same read eventually consistent costs 1; a 7 KB write costs 7 WCU. **On-demand mode** removes capacity planning for a higher per-request price model — the right default until traffic is predictable; **provisioned mode with auto scaling** wins for steady load. A hard truth: a **hot partition key** (one tenant, one celebrity, one 'GLOBAL' counter) concentrates traffic beyond a partition's throughput share and throttles you even though the table has spare capacity — adaptive capacity helps but does not repeal the design requirement to spread keys.\n\nThe supporting cast: **DynamoDB Streams** (ordered change events → Lambda), **TTL** (free deletion by timestamp), **Global Tables** (multi-region, multi-writer, last-writer-wins conflict resolution), **DAX** (microsecond read cache), point-in-time recovery, and full at-rest encryption via KMS.\n\n> **War story:** A ticketing platform put on-sale events behind DynamoDB with partition key = event_id. The biggest on-sale of the year drove every request to one partition: throttling at 4% of table capacity. The fix — write sharding (event_id#00..#15 suffixes, scatter-gather on read) — is a known pattern, but it had to be retrofitted during an incident. Key design *is* capacity design in DynamoDB; model your access patterns first (single-table design), then define keys.\n\n## Consistency: Read the Fine Print Twice\n\n- RDS/Aurora: ACID transactions, strong consistency on the writer; replicas lag asynchronously.\n- DynamoDB: eventually consistent reads by default; strongly consistent on request (2x RCU, not available on GSIs); ACID **transactions** exist (TransactWriteItems) at 2x cost across up to 100 items.\n\nNeither 'eventual' nor 'strong' is a virtue by itself — the question is what your business logic tolerates. Shopping-cart display tolerates eventual; balance transfers do not.\n\n## Decision Framework\n\n1. **Access patterns known, finite, key-shaped, and huge/spiky scale?** DynamoDB. Design keys from access patterns, on-demand mode first.\n2. **Ad-hoc queries, joins, reporting, ORMs, transactions across many entities?** RDS/Aurora PostgreSQL by default.\n3. **Both true?** Both databases — commands in DynamoDB, streams to an analytics store for queries (next lesson), or Aurora with DynamoDB for the hot key-value path. Polyglot persistence is normal, not failure.\n4. **Serverless compute callers?** RDS Proxy in front of RDS; DynamoDB needs nothing.\n5. **Never** choose DynamoDB because 'NoSQL is webscale' or RDS because 'SQL is what we know' without writing the access-pattern list first. The access-pattern list is the whole decision.\n\n> **Pitfall:** Scans. A DynamoDB Scan reads every item and bills every RCU on the way. A weekly analytics Scan of a 2 TB table is a budget event and a throttling event. Export to S3 (native, no RCU cost) and query with Athena instead — which is exactly where the next lesson picks up."},
  "animation_sequence": [
    {"type": "StoryCard", "id": "db_story", "content": "story_variant", "visual_theme": "data_engines", "duration_ms": 4500},
    {"type": "ConceptMap", "id": "db_map", "nodes": ["Access Patterns", "Aurora Writer", "Read Replicas", "DynamoDB Table", "Partition Key Design", "GSI", "DynamoDB Streams"], "edges": [["Access Patterns", "Aurora Writer"], ["Access Patterns", "DynamoDB Table"], ["Aurora Writer", "Read Replicas"], ["DynamoDB Table", "Partition Key Design"], ["DynamoDB Table", "GSI"], ["DynamoDB Table", "DynamoDB Streams"]], "description": {"en": "The decision starts at access patterns, not technology preference. Relational scales reads with replicas; DynamoDB scales everything with key design."}},
    {"type": "ComparisonPanel", "id": "rds_vs_ddb", "left": {"label": "DynamoDB chosen for an ad-hoc reporting workload with joins", "result": false}, "right": {"label": "Keys designed from a written access-pattern list; relational kept for relational questions", "result": true}, "description": {"en": "DynamoDB gives you exactly the queries your keys support at any scale; RDS gives you any query at instance-bounded scale. Match contract to workload."}},
    {"type": "CodeStepper", "id": "rcu_code", "code": "import math\n\ndef read_rcu(item_kb, strong=True):\n    units = math.ceil(item_kb / 4)\n    return units if strong else math.ceil(units / 2)\n\ndef write_wcu(item_kb):\n    return math.ceil(item_kb / 1)", "steps": [{"line": 4, "explanation": {"en": "Reads bill in 4 KB units, rounded UP — a 4.1 KB item costs the same as an 8 KB item."}}, {"line": 5, "explanation": {"en": "Eventually consistent reads cost half. Two eventual reads per RCU is the single biggest lever on read-heavy bills."}}, {"line": 8, "explanation": {"en": "Writes bill per 1 KB — writes are effectively 4x the price of reads for the same bytes. Fat items punish write-heavy tables."}}], "duration_ms": 5000},
    {"type": "TerminalOutput", "id": "ddb_cli", "lines": ["$ aws dynamodb describe-table --table-name orders \\", "    --query 'Table.[BillingModeSummary.BillingMode,ItemCount]'", "[\"PAY_PER_REQUEST\", 18234012]", "$ aws cloudwatch get-metric-statistics --namespace AWS/DynamoDB \\", "    --metric-name ThrottledRequests ... ", "{ \"Datapoints\": [] }"], "description": {"en": "A healthy on-demand table: 18 million items, zero throttles. The empty Datapoints array is the goal state."}},
    {"type": "FlowArrow", "id": "hot_partition_flow", "stages": ["One hot key", "Partition throughput ceiling", "Throttling at low table utilization", "Write sharding (key#00..#15)", "Load spread, throttles gone"], "description": {"en": "The hot-partition failure and its standard cure — key design is capacity design."}}
  ],
  "practice_challenges": [
    {
      "instruction": {"en": "Implement the DynamoDB capacity calculator every table design review runs. Rules: a strongly consistent read costs ceil(item_kb / 4) RCU; an eventually consistent read costs ceil(ceil(item_kb / 4) / 2) RCU; a write costs ceil(item_kb / 1) WCU. Write read_rcu(item_kb, strong) and write_wcu(item_kb), then for ITEM_KB = 7, READS_PER_SEC = 100 and WRITES_PER_SEC = 20, print exactly four lines: 'item_size=7KB reads=100/s writes=20/s', then 'strong_read_rcu=<total>', 'eventual_read_rcu=<total>', 'wcu=<total>' where each total is per-op cost times ops per second. This arithmetic is the difference between a table that costs what you modeled and one that throttles the biggest launch of the year."},
      "starter_code": "import math\n\nITEM_KB = 7\nREADS_PER_SEC = 100\nWRITES_PER_SEC = 20\n\ndef read_rcu(item_kb, strong=True):\n    # TODO: units = ceil(item_kb / 4)\n    # TODO: return units if strong else ceil(units / 2)\n    pass\n\ndef write_wcu(item_kb):\n    # TODO: return ceil(item_kb / 1)\n    pass\n\n# TODO: print f\"item_size={ITEM_KB}KB reads={READS_PER_SEC}/s writes={WRITES_PER_SEC}/s\"\n# TODO: print f\"strong_read_rcu={read_rcu(ITEM_KB, True) * READS_PER_SEC}\"\n# TODO: print f\"eventual_read_rcu={read_rcu(ITEM_KB, False) * READS_PER_SEC}\"\n# TODO: print f\"wcu={write_wcu(ITEM_KB) * WRITES_PER_SEC}\"\n",
      "expected_output": "item_size=7KB reads=100/s writes=20/s\nstrong_read_rcu=200\neventual_read_rcu=100\nwcu=140\n",
      "hints": {"en": ["A 7 KB strong read: ceil(7/4) = 2 RCU. Times 100 reads/s = 200.", "Eventual consistency halves the per-read cost: ceil(2/2) = 1 RCU, so 100 total.", "Writes bill per 1 KB: ceil(7/1) = 7 WCU per write, times 20/s = 140."]},
      "test_code": "assert read_rcu(7, True) == 2\nassert read_rcu(7, False) == 1\nassert read_rcu(4, True) == 1\nassert read_rcu(4.1, True) == 2\nassert write_wcu(7) == 7\nassert write_wcu(0.5) == 1"
    }
  ],
  "quiz": [
    {"q": {"en": "How does Aurora's storage architecture differ from standard RDS?"}, "options": {"en": ["Aurora stores data on instance-local NVMe only", "Aurora uses a distributed storage volume with six copies across three AZs, decoupled from compute", "Aurora replicates synchronously to exactly one standby instance", "Aurora has no automated backups"]}, "correct": 1},
    {"q": {"en": "A DynamoDB table throttles requests while overall consumed capacity is far below provisioned capacity. What is the most likely cause?"}, "options": {"en": ["A hot partition key concentrating traffic on one partition", "The table is in on-demand mode", "TTL deletions are consuming capacity", "GSIs are disabled"]}, "correct": 0},
    {"q": {"en": "One RCU supports which of the following?"}, "options": {"en": ["One write per second up to 1 KB", "Two strongly consistent reads per second up to 4 KB", "One strongly consistent read per second up to 4 KB, or two eventually consistent reads", "One transactional read of any size"]}, "correct": 2},
    {"q": {"en": "What is the recommended way to run heavy analytics over a large DynamoDB table?"}, "options": {"en": ["A parallel Scan with maximum segments during peak hours", "Raise provisioned RCU temporarily and Scan nightly", "Query each partition key sequentially", "Export the table to S3 and query with Athena — no RCU consumption"]}, "correct": 3}
  ],
  "tags": {"concepts_taught": ["aws_data_platform"], "concepts_required": ["aws_networking", "aws_security"], "difficulty": "advanced", "engagement_type": "hands_on", "estimated_minutes": 22, "category": "enterprise_cloud", "path_memberships": []},
  "generated": false
}
