{
  "id": "numpy_operations",
  "topic": "numpy",
  "track": "ai_ml_foundations",
  "module": "numpy",
  "order": 2,
  "title": {
    "en": "NumPy Operations: Vectorised Math & Aggregation",
    "ta": "NumPy செயல்கள்: வெக்டர் செயலாக்கம் மற்றும் தொகுப்பு",
    "te": "NumPy కార్యకలాపాలుః వెక్టర్లైజ్డ్ మథా & అగ్రిగేషన్",
    "ml": "NumPy പ്രവർത്തനങ്ങൾഃ വെക്റ്ററൈസ്ഡ് മാത്തമാറ്റിക്സ് & അഗ്രഗെഷൻ",
    "fr": "Opérations NumPy: mathématiques vectoriées et agrégation",
    "es": "Operaciones NumPy: Matemáticas vectorizadas y agregación",
    "it": "NumPy Operations: matematica e aggregazione vettorizzate",
    "ko": "NumPy 운영: 벡터화된 수학 및 집합"
  },
  "description": {
    "en": "Master element-wise arithmetic, universal functions (ufuncs), and aggregation methods like sum, mean, min, max."
  },
  "xp_reward": 60,
  "next_unlock": "numpy_broadcasting",
  "story_variants": {
    "en": "## NumPy Operations: Math Without Loops\n\nOne of NumPy's greatest powers is performing operations on **every element at once** — no `for` loop needed. This is called **vectorisation**.\n\n### Element-wise Arithmetic\n\nWhen you add, subtract, multiply or divide two arrays of the same shape, the operation happens element by element:\n\n```python\nimport numpy as np\n\na = np.array([1, 2, 3, 4])\nb = np.array([10, 20, 30, 40])\n\nprint(a + b)    # [11 22 33 44]\nprint(b - a)    # [ 9 18 27 36]\nprint(a * b)    # [ 10  40  90 160]\nprint(b / a)    # [10. 10. 10. 10.]\nprint(a ** 2)   # [ 1  4  9 16]\n```\n\n### Universal Functions (ufuncs)\n\nNumPy provides **ufuncs** — functions that apply element-wise automatically:\n\n| Function | Description |\n|----------|-------------|\n| `np.sqrt(a)` | Square root of each element |\n| `np.abs(a)` | Absolute value |\n| `np.exp(a)` | e raised to each element |\n| `np.log(a)` | Natural log of each element |\n| `np.sin(a)` | Sine of each element |\n\n### Aggregation Methods\n\nAggregate all elements into a single value (or along an axis):\n\n```python\nm = np.array([[1, 2, 3],\n              [4, 5, 6]])\n\nprint(m.sum())          # 21  — sum of all elements\nprint(m.mean())         # 3.5 — mean of all elements\nprint(m.min())          # 1\nprint(m.max())          # 6\nprint(m.sum(axis=0))    # [5 7 9]  — sum each column\nprint(m.sum(axis=1))    # [ 6 15] — sum each row\nprint(m.std())          # standard deviation\n```\n\n> **Key Concept:** The `axis` parameter tells NumPy which dimension to collapse. `axis=0` collapses rows (giving per-column results). `axis=1` collapses columns (giving per-row results).",
    "ta": "## NumPy செயல்கள்: சுழற்சிகள் இல்லாமல் கணிதம்\n\nNumPy இன் மிகப்பெரும் சக்திகளில் ஒன்று, **ஒவ்வொரு உறுப்பினரையும் ஒரே நேரத்தில்** செயல்படுத்துவது — `for` சுழற்சி தேவையில்லை. இதற்கு **வெக்டரைசேஷன்** (vectorisation) என்று சொல்லப்படுகிறது.\n\n### உறுப்புக்கு உறுப்பு கணிதம்\n\nஇரண்டு ஒரே வடிவமைப்பில் உள்ள வரிசைகளைச் சேர்த்து, கழிக்க, பெருக்க அல்லது வகுக்கும்போது, அசைவு ஒவ்வொரு உறுப்பிற்கும் ஒருவருக்கொருவராக நடைபெறுகிறது:```python\nimport numpy as np\n\na = np.array([1, 2, 3, 4])\nb = np.array([10, 20, 30, 40])\n\nprint(a + b)    # [11 22 33 44]\nprint(b - a)    # [ 9 18 27 36]\nprint(a * b)    # [ 10  40  90 160]\nprint(b / a)    # [10. 10. 10. 10.]\nprint(a ** 2)   # [ 1  4  9 16]\n```### உலகளாவிய செயல்பாடுகள் (ufuncs)\n\nNumPy **ufuncs** — ஒவ்வொரு உறுப்பிற்கும் தானாகவே செயல்படுத்தப்படும் செயல்பாடுகளை வழங்குகிறது:\n\n| செயல்பாடு | விளக்கம் |\n|----------|-------------|\n| `np.sqrt(a)` | ஒவ்வொரு உறுப்பின் வர்க்க மூலம் |\n| `np.abs(a)` | மீதித்தொகை (மதிப்பு) |\n| `np.exp(a)` | ஒவ்வொரு உறுப்பிற்கும் e-ஐ உயர்த்துதல் |\n| `np.log(a)` | ஒவ்வொரு உறுப்பின் இயற்கணித மடக்கை |\n| `np.sin(a)` | ஒவ்வொரு உறுப்பின் சைன் (Sine) |\n\n### சேகரிப்பு முறைகள் (Aggregation Methods)\n\nஅனைத்து உறுப்புகளையும் ஒரு ஒற்றை மதிப்பாக (அல்லது ஒரு அச்சிற்கு ஏற்ப) சேர்க்கவும்:```python\nm = np.array([[1, 2, 3],\n              [4, 5, 6]])\n\nprint(m.sum())          # 21  — sum of all elements\nprint(m.mean())         # 3.5 — mean of all elements\nprint(m.min())          # 1\nprint(m.max())          # 6\nprint(m.sum(axis=0))    # [5 7 9]  — sum each column\nprint(m.sum(axis=1))    # [ 6 15] — sum each row\nprint(m.std())          # standard deviation\n```> **முக்கிய கருத்து:** `axis` பராமரிப்பு என்பது NumPy இல் எந்த அளவுருவை சுருக்க வேண்டும் என்பதைக் கூறுகிறது. `axis=0` வரிசைகளை சுருக்குகிறது (ஒவ்வொரு நெடுவரிசைக்கும் முடிவுகளைக் கொடுக்கிறது). `axis=1` நெடுவரிசைகளை சுருக்குகிறது (ஒவ்வொரு வரிக்கும் முடிவுகளைக் கொடுக்கிறது)."
  },
  "animation_sequence": [
    {
      "type": "StoryCard",
      "id": "intro_card",
      "content": "story_variant",
      "duration_ms": 4000
    },
    {
      "type": "CodeStepper",
      "id": "elementwise_ops",
      "steps": [
        {
          "line": "a = np.array([1, 2, 3, 4])",
          "highlight": "np.array",
          "explanation": {
            "en": "Create a simple integer array"
          }
        },
        {
          "line": "b = np.array([10, 20, 30, 40])",
          "highlight": "np.array",
          "explanation": {
            "en": "Create a second array of the same shape"
          }
        },
        {
          "line": "print(a + b)",
          "highlight": "+",
          "explanation": {
            "en": "Add each corresponding pair of elements"
          },
          "output": "[11 22 33 44]"
        },
        {
          "line": "print(a ** 2)",
          "highlight": "**",
          "explanation": {
            "en": "Square every element in a"
          },
          "output": "[ 1  4  9 16]"
        },
        {
          "line": "print(m.sum(axis=0))",
          "highlight": "axis=0",
          "explanation": {
            "en": "Sum down each column"
          },
          "output": "[5 7 9]"
        }
      ]
    },
    {
      "type": "DataStructure",
      "id": "matrix_agg",
      "structure_type": "matrix",
      "data": [
        [
          1,
          2,
          3
        ],
        [
          4,
          5,
          6
        ]
      ],
      "highlight_color": "#4f8ef7"
    },
    {
      "type": "ComparisonPanel",
      "id": "axis_compare",
      "left": {
        "label": "axis=0 (collapse rows)",
        "code": "m.sum(axis=0)\n# [5, 7, 9]",
        "note": "One result per column"
      },
      "right": {
        "label": "axis=1 (collapse columns)",
        "code": "m.sum(axis=1)\n# [6, 15]",
        "note": "One result per row"
      }
    },
    {
      "type": "TerminalOutput",
      "id": "agg_output",
      "output": [
        "sum → 21",
        "mean → 3.5",
        "min → 1",
        "max → 6",
        "std → 1.708..."
      ]
    },
    {
      "type": "ExecutionVisualizer",
      "id": "ev_numpy_ops",
      "code": "import numpy as np\n\na = np.array([1, 2, 3, 4])\nb = np.array([10, 20, 30, 40])\nprint(a + b)\nprint(a * b)\nprint(a ** 2)\nprint(np.sqrt(b))\nprint(np.sum(a))\nprint(np.mean(b))",
      "executionSteps": [
        {
          "line": 1,
          "variables": {},
          "output": "",
          "explanation": "Import NumPy"
        },
        {
          "line": 3,
          "variables": {
            "a": "[1, 2, 3, 4]"
          },
          "output": "",
          "explanation": "Create array a"
        },
        {
          "line": 4,
          "variables": {
            "b": "[10, 20, 30, 40]"
          },
          "output": "",
          "explanation": "Create array b"
        },
        {
          "line": 5,
          "variables": {
            "a + b": "[11, 22, 33, 44]"
          },
          "output": "[11 22 33 44]",
          "explanation": "Element-wise addition — no loop needed"
        },
        {
          "line": 6,
          "variables": {
            "a * b": "[10, 40, 90, 160]"
          },
          "output": "[ 10  40  90 160]",
          "explanation": "Element-wise multiplication"
        },
        {
          "line": 7,
          "variables": {
            "a ** 2": "[1, 4, 9, 16]"
          },
          "output": "[ 1  4  9 16]",
          "explanation": "Element-wise squaring"
        },
        {
          "line": 8,
          "variables": {
            "np.sqrt(b)": "[3.16, 4.47, 5.48, 6.32]"
          },
          "output": "[3.16227766 4.47213595 5.47722558 6.32455532]",
          "explanation": "Element-wise square root"
        },
        {
          "line": 9,
          "variables": {
            "np.sum(a)": "10"
          },
          "output": "10",
          "explanation": "Sum all elements: 1+2+3+4 = 10"
        },
        {
          "line": 10,
          "variables": {
            "np.mean(b)": "25.0"
          },
          "output": "25.0",
          "explanation": "Mean: (10+20+30+40)/4 = 25.0"
        }
      ]
    }
  ],
  "practice_challenges": [
    {
      "instruction": {
        "en": "Create a 2-D NumPy array called `scores` with shape (3, 4) filled with integers of your choice. Compute `row_means` as the mean of each row.",
        "ta": "`scores` என்ற வடிவமைப்பு (3, 4) கொண்ட ஒரு 2-பக்க நியூம்பி வரிசையை உருவாக்கவும், உங்கள் விருப்பத்திற்கேற்ப முழு எண்களால் நிரப்பவும். `row_means` ஐ ஒவ்வொரு வரிசையின் சராசரியாகக் கணக்கிடவும்.",
        "te": "`scores`అని పిలువబడే 2-D NumPy అమరికను సృష్టించండి, మీ ఎంపిక యొక్క పూర్ణాంకాలతో నిండిన ఆకారం (3, 4) తో.`row_means` ను ప్రతి వరుస యొక్క సగటుగా లెక్కించండి.",
        "ml": "`scores`എന്ന 2-D NumPy അറേ സൃഷ്ടിക്കുക, നിങ്ങളുടെ ഇഷ്ടം നിറഞ്ഞ പൂജ്യ സംഖ്യകളുള്ള (3, 4) രൂപം. ഓരോ വരിയുടെയും ശരാശരി`row_means` ആയി കണക്കാക്കുക.",
        "fr": "Créer un tableau 2D numérique numérique appelé `scores` avec la forme (3, 4) remplie de nombres entiers de votre choix.",
        "es": "Crea una matriz de 2D NumPy llamada `scores` con forma (3, 4) llena de enteros de tu elección.",
        "it": "Crea una matrice NumPy 2-D chiamata `scores` con forma (3, 4) piena di numeri interi di tua scelta.",
        "ko": "`scores`라는 2D NumPy 배열을 생성하여, 3, 4의 모양으로 선택된 정수들로 채워집니다. 각 줄의 평균으로 `row_means`를 계산합니다."
      },
      "hints": [
        {
          "en": "Use np.array([...]) with nested lists to create a 3x4 matrix"
        },
        {
          "en": "row_means = scores.mean(axis=1) gives a mean per row"
        }
      ],
      "test_code": "import numpy as np\nassert isinstance(scores, np.ndarray), 'scores must be a numpy array'\nassert scores.shape == (3, 4), 'scores must be shape (3, 4)'\nassert isinstance(row_means, np.ndarray), 'row_means must be a numpy array'\nassert row_means.shape == (3,), 'row_means must have 3 values (one per row)'"
    },
    {
      "instruction": {
        "en": "Given `arr = np.array([-3, -1, 0, 2, 5])`, create `abs_arr` using np.abs and `squared` by squaring arr."
      },
      "hints": [
        {
          "en": "abs_arr = np.abs(arr)"
        },
        {
          "en": "squared = arr ** 2"
        }
      ],
      "test_code": "import numpy as np\narr = np.array([-3, -1, 0, 2, 5])\nassert np.array_equal(abs_arr, np.abs(arr)), 'abs_arr must be the absolute values'\nassert np.array_equal(squared, arr**2), 'squared must be arr squared'"
    }
  ],
  "generated": false,
  "speed_multiplier": 1.0,
  "tags": {
    "concepts_taught": [
      "numpy_basics"
    ],
    "concepts_required": [
      "numpy_basics"
    ],
    "difficulty": "intermediate",
    "engagement_type": "hands_on",
    "estimated_minutes": 25,
    "real_world_application": [],
    "category": "data_science",
    "path_memberships": []
  }
}